## 类型信息
多态，从通用基类继承出新的数据类型，运行时动态绑定，向上转型，不需要知道任何特殊信息即可完成操作。
让代码只操纵对基类的引用，基类动态绑定方法，子类覆盖方法，使用泛化的基类引用来调用，由于是
动态绑定的，也能产生正确的行为。

多态是面向对象编程的基本目标

当在运行时需要识别类和对象的信息时，采用：
* 运行时类型识别(RTTI)
* 反射机制：运行时发现和使用类信息
### RTTI
#### Class对象
包含了类有关的信息，每个类都有一个Class对象（被保存在同名.class文件中`out/jvm/production/xx.class`），通过JVM的类加载器进行加载。
所有的类都是在对其第一次使用时动态加载到JVM中，当程序创建第一个对类的静态成员的引用时，就会加载这个类。
（构造器也时类的静态方法，`new xx()`会被当作对类静态成员的引用，进行类加载）

[类加载][1]过程：
* 首先检查这个类的Class对象是否已经加载；
* 若尚未加载，默认的类加载器会根据全限定类名查找.class文件进行类加载（ClassLoader）；
	* 加载：这是由类加载器（ClassLoader）执行的。通过一个类的全限定名来获取其定
	义的二进制字节流（class字节码.class文件），将这个字节流所代表的静态存
	储结构转化为方法去的运行时数据接口，根据字节码在JVM堆中生成一个代表
	这个类的java.lang.Class对象；
	* 链接验证：在链接阶段将验证class文件中的字节流包含的信息是否符合当前虚拟机的
	要求，为静态域分配存储空间并设置类变量的初始值（默认的零值），并且如
	果必需的话，将常量池中的符号引用转化为直接引用;
	* 初始化：到了此阶段，才真正开始执行类中定义的java程序代码。用于执行该类的静态
	初始器和静态初始块，如果该类有父类的话，则优先对其父类进行初始化。
* 一旦某个类的Class对象被载入内存（JVM堆），它就被用来创建这个类的所有对象。
```Java
//Class对象
public class ClassLoading {
    public static void main(String[] args) {
        System.out.println("inside main");
        new Candy();
        try {
            //Class.forName()获取类的Class对象，若没有则进行类加载
            Class.forName("Gum");
        } catch (ClassNotFoundException e) {
            System.out.println("not find gum");
        }
        System.out.println("after Class.forName(\"Gum\")");
        new Cookie();
        System.out.println("after create cookie");
    }
}
class Candy {
    // new xx()触发类加载过程
    // 类加载过程第三步初始化，初始化顺序为
    // 父类static变量->父类static块->子类static变量->子类static块->
    // 父类变量->父类代码块->父类构造函数->子类变量->子类代码块->子类构造函数
    static {
        System.out.println("loading candy");
    }
    public Candy() {
        System.out.println("initial candy");
    }
}

class Gum {
    static {
        System.out.println("loading gum");
    }
}

class Cookie {
    static {
        System.out.println("loading cookie");
    }
}
//inside main
loading candy
initial candy
loading gum
after Class.forName("Gum")
loading cookie
after create cookie
```
#### Class对象的获取方式
* `Class.forName("类的全限名");` ：Class类的static方法，返回Class对象的引用，若类未加载进行类加载；
* `实例对象.getClass();`：Object方法，返回该对象实际类型的Class引用；
* `类名.class;(类字面变量)`：保持与普通类的一致性，不会自动初始化该Class对象。
初始化延迟到了对静态方法或非常数静态域(编译器常量 `static final = 1`除外)进行首次引用时才执行。
```Java
import java.util.Random;

public class MyTest2 {
    public static void main(String[] args) {
        System.out.println(MyParent2.i);

        System.out.println(MyParent2.i2);
    }
}

class MyParent2 {
    public static final int i = 3; //编译时常量，不需要进行类加载就可读取
    public static final int i2 = new Random(47).nextInt(1000); //运行时常量，主动使用常量所在类，触发类加载

    static{
        System.out.println("Myparent2 static block");
    }
}
//3
Myparent2 static block
258
```
具体过程
```Java
Compiled from "MyTest2.java"
public class MyTest2 {
  public MyTest2();
    Code:
       0: aload_0
       1: invokespecial #1                  // Method java/lang/Object."<init>":()V
       4: return

  public static void main(java.lang.String[]);
    Code:
       0: getstatic     #2                  // Field java/lang/System.out:Ljava/io/PrintStream;
       3: iconst_3
       4: invokevirtual #4                  // Method java/io/PrintStream.println:(I)V
       7: getstatic     #2                  // Field java/lang/System.out:Ljava/io/PrintStream;
      10: getstatic     #5                  // Field MyParent2.i2:I
      13: invokevirtual #4                  // Method java/io/PrintStream.println:(I)V
      16: return
}
```
其在在打印`i`时，第三行`3: iconst_3`表明和对象无关；在打印`i2`时
`10: getstatic     #5                  // Field MyParent2.i2:I`表明使用了`MyParent2`类，
需要进行类初始化过程。

Class ADT
```Java
//java.lang.Class.java
class Class {
    String toString();//返回 接口 ? "interface" : (基本类型 ? "" : "class ") + getName();
    String getName(); //name
    boolean isInterface();
    Class<?>[] getInterfaces();//返回实现的接口
    Class forName();//获取Class对象引用
    Class getSuperClass();//父类Class对象引用
    T newInstance();//创建对象，虚拟构造器的方法	
    ClassLoader getClassLoader();//获取类加载器
}
```
类型转换（向下转型）错误，会抛出`ClassCastExcpetion`异常。`instanceof`告诉对象是否是某个特定类的具体实例。
#### 随机创建不同类型的宠物
```Java
class Pet {
}
class Dog extends Pet {
}
class Mutt extends Dog {
}
//......
//随机创建不同类型的宠物
abstract class PetCreator {
    private Random rand = new Random(47);
    abstract List<Class<? extends Pet>> types(); //抽象方法--实现类实现包含所有Pet类型
    
    public Pet RandomPet() {
        int n = rand.nextInt(types().size());
        try {
            return types().get(n).newInstance();
        } catch(Exception e) {
            //InstantiationException
            //IllegalAccessException--默认构造函数私有
        }
    }		
}
```
`types()`方法返回静态`List`的引用(Class对象)。
```Java
class ForNameCreator extends PetCreator {
    private static List<Class<? extends Pet>> types = new ArrayList<Class<? extends Pet>>();
    private static String[] typesName = {"xx.pets.Mutt",...}; //添加新类需要修改
    //将typesName逐一通过Class.forName()转化为Class对象
    @SuppressWarnings("unchecked")
    static void loader(){}
    static {
        loader();
    }
    //覆盖abstract方法
    public List<Class<? extends Pet>> types() {return types;}
}
```
需要计数的话采用`Map`进行计数。

`Class.isInstance()`方法动态的测试对象，也可以使用递归计数的方式`Class.isAssignableFrom()`，在对
一个类型进行计数之后，若其有父类，则对父类进行计数`countClass(superClass)`。
```Java
//Pet为基类，PetCount统计各种类型Pet的数量
class PetCount {
    static class PetCounter extends Map<Class<? extends Pet>, Interger> {
        public PetCounter() {
            //allTypes为Pet的所有类型
            super(MapData.map(allTypes, 0));//初始化为所有类型的Map
        }
        public void count(Pet pet) {
            for (Map.Entry<Class<? extends Pet>, Interger> pair : entrySet()) {
                if (pair.getKey().isInstance(pet)) {
                    put(pair.getKey(), pair.getValue() + 1);
                }
            }
        }
    }
}
```
但上述方式创建对象存在问题：添加新的子类(extends Pet)需要修改`Creator`类中的`types`。（开闭原则）故而
可以采用注册工厂的方式进行创建，有实现子类自己进行对象的创建。

`instanceof方法和isInstance`可以保留继承的结果（子类对象 isInstanceof 父类.class），而
`equals && ==`只是单纯的比较Class对象是否相同。
### 反射机制
`java.lang.reflect`，与RTTI不同在于运行时.class文件才可访问。

反射从Class对象中获取类信息。
```Java
//Field
Field[] getDeclaredFields();//获取所有成员变量-->内部暴露/安全问题
Field getDeclaredField(String name);

void set(Object obj, Object value);
Object get(Object obj);

//Constructor
Constructor<?>[] getConstructors();
Constructor<?>[] getDeclaredConstructors();

//Method
Method[] getMethods();
Method[] getDeclaredMethods();

//
String getName();
```
[1]:http://
